Workbook

Sheet 使用说明
A1: AI多因子透视诊断 — 金融模型 v2.0
A3: 模型概述
B4: 本模型实现"AI多因子透视诊断"系统的完整Excel计算引擎，包含5套子模型并行打分 + 动态权重调整 + 综合输出。
A6: 颜色规范
B7: 🔵 蓝色字体 = 硬编码输入值（用户可修改的假设/数据）
B8: ⚫ 黑色字体 = Excel 公式和计算
B9: 🟢 绿色字体 = 跨 Sheet 引用
B10: 🔴 红色字体 = 跨文件引用
B11: 🟡 黄色底色 = 需要关注的重要假设/需定期更新的单元格
A13: Sheet 结构
B14: ① 使用说明 — 本页
B15: ② 假设区 — 市场环境参数、行业基准数据、评分阈值
B16: ③ 基金持仓 — 重仓股明细（蓝色输入）
B17: ④ M1_个股质量评分 — 个股质量加权评分模型（权重25%）
B18: ⑤ M2_估值评分 — 估值性价比模型（权重25%）
B19: ⑥ M3_舆情评分 — 新闻舆情与动量模型（权重20%）
B20: ⑦ M4_行业景气 — 行业前景与宏观匹配模型（权重15%）
B21: ⑧ M5_经理行为 — 基金经理行为一致性模型（权重15%）
B22: ⑨ 动态权重 — 市场环境识别 + 动态权重调整引擎
B23: ⑩ 综合输出 — 仪表盘、综合评分、操作建议
A25: 使用方法
B26: 1. 在「假设区」更新市场环境参数和行业基准数据
B27: 2. 在「基金持仓」填入待分析基金的持仓明细
B28: 3. 在 M1~M5 各 Sheet 填入每只股票/行业的蓝色输入数据
B29: 4. 模型自动计算各维度得分和综合评分
B30: 5. 在「综合输出」查看最终诊断结果

Sheet 假设区
A1: 市场环境参数（需定期更新）
A2: 参数名称 | B2: 当前值 | C2: 单位 | D2: 更新频率
A3: 沪深300 PE分位数 | B3: 0.65 | C3: % | D3: 日
A4: 沪深300 PE_TTM | B4: 14.82 | C4: 倍 | D4: 日
A5: 10Y国债收益率 | B5: 0.0285 | C5: % | D5: 日
A6: EPU指数分位数 | B6: 0.55 | C6: % | D6: 月
A7: 市场波动率分位数(60日) | B7: 0.5 | C7: % | D7: 日
A8: 60日均线/200日均线比值 | B8: 1.02 | C8: 倍 | D8: 日
A9: CPI YoY | B9: 0.008 | C9: % | D9: 月
A10: USDCNY | B10: 7.25 | D10: 日
A12: 模型默认权重
A13: 模型 | B13: 代号 | C13: 默认权重 | D13: 牛市权重 | E13: 熊市权重 | F13: 高不确定性权重
A14: 个股质量加权评分 | B14: M1 | C14: 0.25 | D14: 0.15 | E14: 0.3 | F14: 0.2
A15: 估值性价比 | B15: M2 | C15: 0.25 | D15: 0.35 | E15: 0.2 | F15: 0.25
A16: 新闻舆情与动量 | B16: M3 | C16: 0.2 | D16: 0.15 | E16: 0.15 | F16: 0.15
A17: 行业前景与宏观匹配 | B17: M4 | C17: 0.15 | D17: 0.2 | E17: 0.2 | F17: 0.3
A18: 基金经理行为一致性 | B18: M5 | C18: 0.15 | D18: 0.15 | E18: 0.15 | F18: 0.1
A20: 行业基准数据（申万一级，2025年报）
A21: 行业名称 | B21: ROE中位数 | C21: 毛利率中位数 | D21: 资产负债率中位数 | E21: PE中位数
A22: 食品饮料 | B22: 0.158 | C22: 0.486 | D22: 0.321 | E22: 25.3
A23: 医药生物 | B23: 0.082 | C23: 0.523 | D23: 0.317 | E23: 32.5
A24: 电子 | B24: 0.065 | C24: 0.248 | D24: 0.382 | E24: 35.1
A25: 电力设备 | B25: 0.091 | C25: 0.224 | D25: 0.526 | E25: 22.8
A26: 银行 | B26: 0.105 | C26: N/A | D26: 0.915 | E26: 5.8
A27: 计算机 | B27: 0.048 | C27: 0.356 | D27: 0.321 | E27: 48.2
A30: 综合评分等级阈值
A31: 评分区间 | B31: 等级 | C31: 操作建议基调
A32: 0.8 | B32: 优秀 ⭐⭐⭐⭐⭐ | C32: 适合作为核心配置
A33: 0.7 | B33: 良好 ⭐⭐⭐⭐ | C33: 可持有，关注风险点
A34: 0.55 | B34: 一般 ⭐⭐⭐ | C34: 观望，等待更好时机
A35: 0.4 | B35: 较低 ⭐⭐ | C35: 建议减仓或寻找替代品
A36: 0 | B36: 差 ⭐ | C36: 强烈建议回避

Sheet 基金持仓
A1: 基金持仓明细（蓝色 = 需手动输入）
A2: 股票代码 | B2: 股票名称 | C2: 占净值比例 | D2: 所属行业 | E2: 近季度仓位变化 | F2: 归一化权重(分析池) | G2: 占分析池权重
A3: 600519 | B3: 贵州茅台 | C3: 0.082 | D3: 食品饮料 | E3: 0.005 | F3: =C3/SUM(C3:C12) | G3: =F3
A4: 300750 | B4: 宁德时代 | C4: 0.065 | D4: 电力设备 | E4: -0.012 | F4: =C4/SUM(C3:C12) | G4: =F4
A5: 600036 | B5: 招商银行 | C5: 0.058 | D5: 银行 | E5: 0.008 | F5: =C5/SUM(C3:C12) | G5: =F5
A6: 300760 | B6: 迈瑞医疗 | C6: 0.049 | D6: 医药生物 | E6: 0.003 | F6: =C6/SUM(C3:C12) | G6: =F6
A7: 002475 | B7: 立讯精密 | C7: 0.045 | D7: 电子 | E7: -0.005 | F7: =C7/SUM(C3:C12) | G7: =F7
A8: 000858 | B8: 五粮液 | C8: 0.038 | D8: 食品饮料 | E8: -0.01 | F8: =C8/SUM(C3:C12) | G8: =F8
A9: 600276 | B9: 恒瑞医药 | C9: 0.032 | D9: 医药生物 | E9: 0.015 | F9: =C9/SUM(C3:C12) | G9: =F9
A10: 688111 | B10: 金山办公 | C10: 0.029 | D10: 计算机 | E10: 0.02 | F10: =C10/SUM(C3:C12) | G10: =F10
A11: 300274 | B11: 阳光电源 | C11: 0.026 | D11: 电力设备 | E11: -0.008 | F11: =C11/SUM(C3:C12) | G11: =F11
A12: 002415 | B12: 海康威视 | C12: 0.023 | D12: 电子 | E12: 0.002 | F12: =C12/SUM(C3:C12) | G12: =F12
B13: 合计 | C13: =SUM(C3:C12) | F13: =SUM(F3:F12)

Sheet M1_个股质量评分
A1: 模型1：个股质量加权评分（默认权重25%）
A2: 代码 | B2: 名称 | C2: 权重 | D2: 行业 | E2: ROE | F2: ROE得分 | G2: 毛利率 | H2: 行业毛利率中位数 | I2: 毛利率得分 | J2: 净利增速 | K2: 净利增速得分 | L2: 营收增速 | M2: 营收增速得分 | N2: OCF/NI | O2: OCF得分 | P2: FCF/Rev | Q2: FCF得分 | R2: 资产负债率 | S2: 行业负债率中位数 | T2: 负债率得分 | U2: 速动比率 | V2: 速动比率得分 | W2: 盈利能力 | X2: 成长性 | Y2: 现金流 | Z2: 安全性 | AA2: 个股质量总分 | AB2: 加权贡献
A3: ='基金持仓'!A3 | B3: ='基金持仓'!B3 | C3: ='基金持仓'!F3 | D3: ='基金持仓'!D3 | E3: 0.32 | F3: =IF(E3>=0.25,100,IF(E3>=0.2,90,IF(E3>=0.15,75,IF(E3>=0.1,55,IF(E3>=0.05,35,IF(E3>=0,20,5)))))) | G3: 0.918 | H3: =IFERROR(VLOOKUP(D3,假设区!A22:C27,3,FALSE),"N/A") | I3: =IF(OR(G3="N/A",H3="N/A"),50,MIN(100,MAX(0,50+50*(G3-H3)/0.15))) | J3: 0.18 | K3: =IF(J3>=0.5,100,IF(J3>=0.3,85,IF(J3>=0.15,70,IF(J3>=0.05,50,IF(J3>=0,30,IF(J3>=-0.1,15,5)))))) | L3: 0.16 | M3: =IF(L3>=0.3,100,IF(L3>=0.2,85,IF(L3>=0.1,65,IF(L3>=0.05,45,IF(L3>=0,25,10))))) | N3: 1.15 | O3: =IF(N3="N/A",50,IF(N3>=1.5,100,IF(N3>=0.5,60+40*(N3-0.5)/1.0,IF(N3>=0,60*N3/0.5,10)))) | P3: 0.42 | Q3: =IF(P3="N/A",50,IF(P3>=0.15,100,IF(P3>=0.1,85,IF(P3>=0.05,65,IF(P3>=0,40,15))))) | R3: 0.19 | S3: =IFERROR(VLOOKUP(D3,假设区!A22:D27,4,FALSE),"N/A") | T3: =IF(OR(R3="N/A",S3="N/A"),50,MAX(0,MIN(100,100-80*R3/(S3*1.3)))) | U3: 2.8 | V3: =IF(U3="N/A",50,IF(U3>=1.5,100,IF(U3>=1,80,IF(U3>=0.7,55,IF(U3>=0.4,30,10))))) | W3: =0.6*F3+0.4*I3 | X3: =0.55*K3+0.45*M3 | Y3: =0.6*O3+0.4*Q3 | Z3: =0.6*T3+0.4*V3 | AA3: =0.3*W3+0.25*X3+0.25*Y3+0.2*Z3 | AB3: =C3*AA3
A4: ='基金持仓'!A4 | B4: ='基金持仓'!B4 | C4: ='基金持仓'!F4 | D4: ='基金持仓'!D4 | E4: 0.22 | F4: =IF(E4>=0.25,100,IF(E4>=0.2,90,IF(E4>=0.15,75,IF(E4>=0.1,55,IF(E4>=0.05,35,IF(E4>=0,20,5)))))) | G4: 0.26 | H4: =IFERROR(VLOOKUP(D4,假设区!A22:C27,3,FALSE),"N/A") | I4: =IF(OR(G4="N/A",H4="N/A"),50,MIN(100,MAX(0,50+50*(G4-H4)/0.15))) | J4: 0.35 | K4: =IF(J4>=0.5,100,IF(J4>=0.3,85,IF(J4>=0.15,70,IF(J4>=0.05,50,IF(J4>=0,30,IF(J4>=-0.1,15,5)))))) | L4: 0.45 | M4: =IF(L4>=0.3,100,IF(L4>=0.2,85,IF(L4>=0.1,65,IF(L4>=0.05,45,IF(L4>=0,25,10))))) | N4: 0.85 | O4: =IF(N4="N/A",50,IF(N4>=1.5,100,IF(N4>=0.5,60+40*(N4-0.5)/1.0,IF(N4>=0,60*N4/0.5,10)))) | P4: 0.06 | Q4: =IF(P4="N/A",50,IF(P4>=0.15,100,IF(P4>=0.1,85,IF(P4>=0.05,65,IF(P4>=0,40,15))))) | R4: 0.62 | S4: =IFERROR(VLOOKUP(D4,假设区!A22:D27,4,FALSE),"N/A") | T4: =IF(OR(R4="N/A",S4="N/A"),50,MAX(0,MIN(100,100-80*R4/(S4*1.3)))) | U4: 1.1 | V4: =IF(U4="N/A",50,IF(U4>=1.5,100,IF(U4>=1,80,IF(U4>=0.7,55,IF(U4>=0.4,30,10))))) | W4: =0.6*F4+0.4*I4 | X4: =0.55*K4+0.45*M4 | Y4: =0.6*O4+0.4*Q4 | Z4: =0.6*T4+0.4*V4 | AA4: =0.3*W4+0.25*X4+0.25*Y4+0.2*Z4 | AB4: =C4*AA4
A5: ='基金持仓'!A5 | B5: ='基金持仓'!B5 | C5: ='基金持仓'!F5 | D5: ='基金持仓'!D5 | E5: 0.13 | F5: =IF(E5>=0.25,100,IF(E5>=0.2,90,IF(E5>=0.15,75,IF(E5>=0.1,55,IF(E5>=0.05,35,IF(E5>=0,20,5)))))) | G5: N/A | H5: =IFERROR(VLOOKUP(D5,假设区!A22:C27,3,FALSE),"N/A") | I5: =IF(OR(G5="N/A",H5="N/A"),50,MIN(100,MAX(0,50+50*(G5-H5)/0.15))) | J5: 0.06 | K5: =IF(J5>=0.5,100,IF(J5>=0.3,85,IF(J5>=0.15,70,IF(J5>=0.05,50,IF(J5>=0,30,IF(J5>=-0.1,15,5)))))) | L5: 0.03 | M5: =IF(L5>=0.3,100,IF(L5>=0.2,85,IF(L5>=0.1,65,IF(L5>=0.05,45,IF(L5>=0,25,10))))) | N5: N/A | O5: =IF(N5="N/A",50,IF(N5>=1.5,100,IF(N5>=0.5,60+40*(N5-0.5)/1.0,IF(N5>=0,60*N5/0.5,10)))) | P5: N/A | Q5: =IF(P5="N/A",50,IF(P5>=0.15,100,IF(P5>=0.1,85,IF(P5>=0.05,65,IF(P5>=0,40,15))))) | R5: 0.91 | S5: =IFERROR(VLOOKUP(D5,假设区!A22:D27,4,FALSE),"N/A") | T5: =IF(OR(R5="N/A",S5="N/A"),50,MAX(0,MIN(100,100-80*R5/(S5*1.3)))) | U5: N/A | V5: =IF(U5="N/A",50,IF(U5>=1.5,100,IF(U5>=1,80,IF(U5>=0.7,55,IF(U5>=0.4,30,10))))) | W5: =0.6*F5+0.4*I5 | X5: =0.55*K5+0.45*M5 | Y5: =0.6*O5+0.4*Q5 | Z5: =0.6*T5+0.4*V5 | AA5: =0.3*W5+0.25*X5+0.25*Y5+0.2*Z5 | AB5: =C5*AA5
A6: ='基金持仓'!A6 | B6: ='基金持仓'!B6 | C6: ='基金持仓'!F6 | D6: ='基金持仓'!D6 | E6: 0.28 | F6: =IF(E6>=0.25,100,IF(E6>=0.2,90,IF(E6>=0.15,75,IF(E6>=0.1,55,IF(E6>=0.05,35,IF(E6>=0,20,5)))))) | G6: 0.66 | H6: =IFERROR(VLOOKUP(D6,假设区!A22:C27,3,FALSE),"N/A") | I6: =IF(OR(G6="N/A",H6="N/A"),50,MIN(100,MAX(0,50+50*(G6-H6)/0.15))) | J6: 0.22 | K6: =IF(J6>=0.5,100,IF(J6>=0.3,85,IF(J6>=0.15,70,IF(J6>=0.05,50,IF(J6>=0,30,IF(J6>=-0.1,15,5)))))) | L6: 0.19 | M6: =IF(L6>=0.3,100,IF(L6>=0.2,85,IF(L6>=0.1,65,IF(L6>=0.05,45,IF(L6>=0,25,10))))) | N6: 1.25 | O6: =IF(N6="N/A",50,IF(N6>=1.5,100,IF(N6>=0.5,60+40*(N6-0.5)/1.0,IF(N6>=0,60*N6/0.5,10)))) | P6: 0.2 | Q6: =IF(P6="N/A",50,IF(P6>=0.15,100,IF(P6>=0.1,85,IF(P6>=0.05,65,IF(P6>=0,40,15))))) | R6: 0.28 | S6: =IFERROR(VLOOKUP(D6,假设区!A22:D27,4,FALSE),"N/A") | T6: =IF(OR(R6="N/A",S6="N/A"),50,MAX(0,MIN(100,100-80*R6/(S6*1.3)))) | U6: 2.2 | V6: =IF(U6="N/A",50,IF(U6>=1.5,100,IF(U6>=1,80,IF(U6>=0.7,55,IF(U6>=0.4,30,10))))) | W6: =0.6*F6+0.4*I6 | X6: =0.55*K6+0.45*M6 | Y6: =0.6*O6+0.4*Q6 | Z6: =0.6*T6+0.4*V6 | AA6: =0.3*W6+0.25*X6+0.25*Y6+0.2*Z6 | AB6: =C6*AA6
A7: ='基金持仓'!A7 | B7: ='基金持仓'!B7 | C7: ='基金持仓'!F7 | D7: ='基金持仓'!D7 | E7: 0.18 | F7: =IF(E7>=0.25,100,IF(E7>=0.2,90,IF(E7>=0.15,75,IF(E7>=0.1,55,IF(E7>=0.05,35,IF(E7>=0,20,5)))))) | G7: 0.14 | H7: =IFERROR(VLOOKUP(D7,假设区!A22:C27,3,FALSE),"N/A") | I7: =IF(OR(G7="N/A",H7="N/A"),50,MIN(100,MAX(0,50+50*(G7-H7)/0.15))) | J7: 0.25 | K7: =IF(J7>=0.5,100,IF(J7>=0.3,85,IF(J7>=0.15,70,IF(J7>=0.05,50,IF(J7>=0,30,IF(J7>=-0.1,15,5)))))) | L7: 0.32 | M7: =IF(L7>=0.3,100,IF(L7>=0.2,85,IF(L7>=0.1,65,IF(L7>=0.05,45,IF(L7>=0,25,10))))) | N7: 0.72 | O7: =IF(N7="N/A",50,IF(N7>=1.5,100,IF(N7>=0.5,60+40*(N7-0.5)/1.0,IF(N7>=0,60*N7/0.5,10)))) | P7: 0.04 | Q7: =IF(P7="N/A",50,IF(P7>=0.15,100,IF(P7>=0.1,85,IF(P7>=0.05,65,IF(P7>=0,40,15))))) | R7: 0.55 | S7: =IFERROR(VLOOKUP(D7,假设区!A22:D27,4,FALSE),"N/A") | T7: =IF(OR(R7="N/A",S7="N/A"),50,MAX(0,MIN(100,100-80*R7/(S7*1.3)))) | U7: 0.9 | V7: =IF(U7="N/A",50,IF(U7>=1.5,100,IF(U7>=1,80,IF(U7>=0.7,55,IF(U7>=0.4,30,10))))) | W7: =0.6*F7+0.4*I7 | X7: =0.55*K7+0.45*M7 | Y7: =0.6*O7+0.4*Q7 | Z7: =0.6*T7+0.4*V7 | AA7: =0.3*W7+0.25*X7+0.25*Y7+0.2*Z7 | AB7: =C7*AA7
A8: ='基金持仓'!A8 | B8: ='基金持仓'!B8 | C8: ='基金持仓'!F8 | D8: ='基金持仓'!D8 | E8: 0.25 | F8: =IF(E8>=0.25,100,IF(E8>=0.2,90,IF(E8>=0.15,75,IF(E8>=0.1,55,IF(E8>=0.05,35,IF(E8>=0,20,5)))))) | G8: 0.76 | H8: =IFERROR(VLOOKUP(D8,假设区!A22:C27,3,FALSE),"N/A") | I8: =IF(OR(G8="N/A",H8="N/A"),50,MIN(100,MAX(0,50+50*(G8-H8)/0.15))) | J8: 0.14 | K8: =IF(J8>=0.5,100,IF(J8>=0.3,85,IF(J8>=0.15,70,IF(J8>=0.05,50,IF(J8>=0,30,IF(J8>=-0.1,15,5)))))) | L8: 0.11 | M8: =IF(L8>=0.3,100,IF(L8>=0.2,85,IF(L8>=0.1,65,IF(L8>=0.05,45,IF(L8>=0,25,10))))) | N8: 1.1 | O8: =IF(N8="N/A",50,IF(N8>=1.5,100,IF(N8>=0.5,60+40*(N8-0.5)/1.0,IF(N8>=0,60*N8/0.5,10)))) | P8: 0.35 | Q8: =IF(P8="N/A",50,IF(P8>=0.15,100,IF(P8>=0.1,85,IF(P8>=0.05,65,IF(P8>=0,40,15))))) | R8: 0.22 | S8: =IFERROR(VLOOKUP(D8,假设区!A22:D27,4,FALSE),"N/A") | T8: =IF(OR(R8="N/A",S8="N/A"),50,MAX(0,MIN(100,100-80*R8/(S8*1.3)))) | U8: 2.5 | V8: =IF(U8="N/A",50,IF(U8>=1.5,100,IF(U8>=1,80,IF(U8>=0.7,55,IF(U8>=0.4,30,10))))) | W8: =0.6*F8+0.4*I8 | X8: =0.55*K8+0.45*M8 | Y8: =0.6*O8+0.4*Q8 | Z8: =0.6*T8+0.4*V8 | AA8: =0.3*W8+0.25*X8+0.25*Y8+0.2*Z8 | AB8: =C8*AA8
A9: ='基金持仓'!A9 | B9: ='基金持仓'!B9 | C9: ='基金持仓'!F9 | D9: ='基金持仓'!D9 | E9: 0.15 | F9: =IF(E9>=0.25,100,IF(E9>=0.2,90,IF(E9>=0.15,75,IF(E9>=0.1,55,IF(E9>=0.05,35,IF(E9>=0,20,5)))))) | G9: 0.85 | H9: =IFERROR(VLOOKUP(D9,假设区!A22:C27,3,FALSE),"N/A") | I9: =IF(OR(G9="N/A",H9="N/A"),50,MIN(100,MAX(0,50+50*(G9-H9)/0.15))) | J9: 0.1 | K9: =IF(J9>=0.5,100,IF(J9>=0.3,85,IF(J9>=0.15,70,IF(J9>=0.05,50,IF(J9>=0,30,IF(J9>=-0.1,15,5)))))) | L9: 0.08 | M9: =IF(L9>=0.3,100,IF(L9>=0.2,85,IF(L9>=0.1,65,IF(L9>=0.05,45,IF(L9>=0,25,10))))) | N9: 0.95 | O9: =IF(N9="N/A",50,IF(N9>=1.5,100,IF(N9>=0.5,60+40*(N9-0.5)/1.0,IF(N9>=0,60*N9/0.5,10)))) | P9: 0.15 | Q9: =IF(P9="N/A",50,IF(P9>=0.15,100,IF(P9>=0.1,85,IF(P9>=0.05,65,IF(P9>=0,40,15))))) | R9: 0.12 | S9: =IFERROR(VLOOKUP(D9,假设区!A22:D27,4,FALSE),"N/A") | T9: =IF(OR(R9="N/A",S9="N/A"),50,MAX(0,MIN(100,100-80*R9/(S9*1.3)))) | U9: 3.5 | V9: =IF(U9="N/A",50,IF(U9>=1.5,100,IF(U9>=1,80,IF(U9>=0.7,55,IF(U9>=0.4,30,10))))) | W9: =0.6*F9+0.4*I9 | X9: =0.55*K9+0.45*M9 | Y9: =0.6*O9+0.4*Q9 | Z9: =0.6*T9+0.4*V9 | AA9: =0.3*W9+0.25*X9+0.25*Y9+0.2*Z9 | AB9: =C9*AA9
A10: ='基金持仓'!A10 | B10: ='基金持仓'!B10 | C10: ='基金持仓'!F10 | D10: ='基金持仓'!D10 | E10: 0.12 | F10: =IF(E10>=0.25,100,IF(E10>=0.2,90,IF(E10>=0.15,75,IF(E10>=0.1,55,IF(E10>=0.05,35,IF(E10>=0,20,5)))))) | G10: 0.88 | H10: =IFERROR(VLOOKUP(D10,假设区!A22:C27,3,FALSE),"N/A") | I10: =IF(OR(G10="N/A",H10="N/A"),50,MIN(100,MAX(0,50+50*(G10-H10)/0.15))) | J10: 0.4 | K10: =IF(J10>=0.5,100,IF(J10>=0.3,85,IF(J10>=0.15,70,IF(J10>=0.05,50,IF(J10>=0,30,IF(J10>=-0.1,15,5)))))) | L10: 0.35 | M10: =IF(L10>=0.3,100,IF(L10>=0.2,85,IF(L10>=0.1,65,IF(L10>=0.05,45,IF(L10>=0,25,10))))) | N10: 1.5 | O10: =IF(N10="N/A",50,IF(N10>=1.5,100,IF(N10>=0.5,60+40*(N10-0.5)/1.0,IF(N10>=0,60*N10/0.5,10)))) | P10: 0.28 | Q10: =IF(P10="N/A",50,IF(P10>=0.15,100,IF(P10>=0.1,85,IF(P10>=0.05,65,IF(P10>=0,40,15))))) | R10: 0.18 | S10: =IFERROR(VLOOKUP(D10,假设区!A22:D27,4,FALSE),"N/A") | T10: =IF(OR(R10="N/A",S10="N/A"),50,MAX(0,MIN(100,100-80*R10/(S10*1.3)))) | U10: 4 | V10: =IF(U10="N/A",50,IF(U10>=1.5,100,IF(U10>=1,80,IF(U10>=0.7,55,IF(U10>=0.4,30,10))))) | W10: =0.6*F10+0.4*I10 | X10: =0.55*K10+0.45*M10 | Y10: =0.6*O10+0.4*Q10 | Z10: =0.6*T10+0.4*V10 | AA10: =0.3*W10+0.25*X10+0.25*Y10+0.2*Z10 | AB10: =C10*AA10
A11: ='基金持仓'!A11 | B11: ='基金持仓'!B11 | C11: ='基金持仓'!F11 | D11: ='基金持仓'!D11 | E11: 0.2 | F11: =IF(E11>=0.25,100,IF(E11>=0.2,90,IF(E11>=0.15,75,IF(E11>=0.1,55,IF(E11>=0.05,35,IF(E11>=0,20,5)))))) | G11: 0.25 | H11: =IFERROR(VLOOKUP(D11,假设区!A22:C27,3,FALSE),"N/A") | I11: =IF(OR(G11="N/A",H11="N/A"),50,MIN(100,MAX(0,50+50*(G11-H11)/0.15))) | J11: 0.55 | K11: =IF(J11>=0.5,100,IF(J11>=0.3,85,IF(J11>=0.15,70,IF(J11>=0.05,50,IF(J11>=0,30,IF(J11>=-0.1,15,5)))))) | L11: 0.5 | M11: =IF(L11>=0.3,100,IF(L11>=0.2,85,IF(L11>=0.1,65,IF(L11>=0.05,45,IF(L11>=0,25,10))))) | N11: 0.6 | O11: =IF(N11="N/A",50,IF(N11>=1.5,100,IF(N11>=0.5,60+40*(N11-0.5)/1.0,IF(N11>=0,60*N11/0.5,10)))) | P11: -0.02 | Q11: =IF(P11="N/A",50,IF(P11>=0.15,100,IF(P11>=0.1,85,IF(P11>=0.05,65,IF(P11>=0,40,15))))) | R11: 0.58 | S11: =IFERROR(VLOOKUP(D11,假设区!A22:D27,4,FALSE),"N/A") | T11: =IF(OR(R11="N/A",S11="N/A"),50,MAX(0,MIN(100,100-80*R11/(S11*1.3)))) | U11: 0.95 | V11: =IF(U11="N/A",50,IF(U11>=1.5,100,IF(U11>=1,80,IF(U11>=0.7,55,IF(U11>=0.4,30,10))))) | W11: =0.6*F11+0.4*I11 | X11: =0.55*K11+0.45*M11 | Y11: =0.6*O11+0.4*Q11 | Z11: =0.6*T11+0.4*V11 | AA11: =0.3*W11+0.25*X11+0.25*Y11+0.2*Z11 | AB11: =C11*AA11
A12: ='基金持仓'!A12 | B12: ='基金持仓'!B12 | C12: ='基金持仓'!F12 | D12: ='基金持仓'!D12 | E12: 0.16 | F12: =IF(E12>=0.25,100,IF(E12>=0.2,90,IF(E12>=0.15,75,IF(E12>=0.1,55,IF(E12>=0.05,35,IF(E12>=0,20,5)))))) | G12: 0.44 | H12: =IFERROR(VLOOKUP(D12,假设区!A22:C27,3,FALSE),"N/A") | I12: =IF(OR(G12="N/A",H12="N/A"),50,MIN(100,MAX(0,50+50*(G12-H12)/0.15))) | J12: 0.08 | K12: =IF(J12>=0.5,100,IF(J12>=0.3,85,IF(J12>=0.15,70,IF(J12>=0.05,50,IF(J12>=0,30,IF(J12>=-0.1,15,5)))))) | L12: 0.06 | M12: =IF(L12>=0.3,100,IF(L12>=0.2,85,IF(L12>=0.1,65,IF(L12>=0.05,45,IF(L12>=0,25,10))))) | N12: 0.88 | O12: =IF(N12="N/A",50,IF(N12>=1.5,100,IF(N12>=0.5,60+40*(N12-0.5)/1.0,IF(N12>=0,60*N12/0.5,10)))) | P12: 0.1 | Q12: =IF(P12="N/A",50,IF(P12>=0.15,100,IF(P12>=0.1,85,IF(P12>=0.05,65,IF(P12>=0,40,15))))) | R12: 0.35 | S12: =IFERROR(VLOOKUP(D12,假设区!A22:D27,4,FALSE),"N/A") | T12: =IF(OR(R12="N/A",S12="N/A"),50,MAX(0,MIN(100,100-80*R12/(S12*1.3)))) | U12: 1.8 | V12: =IF(U12="N/A",50,IF(U12>=1.5,100,IF(U12>=1,80,IF(U12>=0.7,55,IF(U12>=0.4,30,10))))) | W12: =0.6*F12+0.4*I12 | X12: =0.55*K12+0.45*M12 | Y12: =0.6*O12+0.4*Q12 | Z12: =0.6*T12+0.4*V12 | AA12: =0.3*W12+0.25*X12+0.25*Y12+0.2*Z12 | AB12: =C12*AA12
B13: M1 综合得分 | AB13: =SUM(AB3:AB12)

Sheet M2_估值评分
A1: 模型2：估值性价比（默认权重25%）
A2: 代码 | B2: 名称 | C2: 权重 | D2: 行业 | E2: PE_TTM | F2: PE分位数 | G2: PE得分 | H2: PB_TTM | I2: PB分位数 | J2: PB得分 | K2: PEG | L2: PEG得分 | M2: 股息率 | N2: 股息率得分 | O2: 行业类型 | P2: PE权重 | Q2: PB权重 | R2: PEG权重 | S2: 股息率权重 | T2: 估值总分 | U2: 加权贡献
A3: ='基金持仓'!A3 | B3: ='基金持仓'!B3 | C3: ='基金持仓'!F3 | D3: ='基金持仓'!D3 | E3: 32.5 | F3: 0.78 | G3: =IF(F3<=0.15,100,IF(F3<=0.3,85,IF(F3<=0.5,65,IF(F3<=0.7,45,IF(F3<=0.85,25,10))))) | H3: 9.5 | I3: 0.72 | J3: =IF(I3<=0.15,100,IF(I3<=0.3,85,IF(I3<=0.5,65,IF(I3<=0.7,45,IF(I3<=0.85,25,10))))) | K3: 1.8 | L3: =IF(K3<0.5,100,IF(K3<0.8,90,IF(K3<1,80,IF(K3<1.5,60,IF(K3<2.5,35,15))))) | M3: 0.018 | N3: =IF(M3>=0.05,100,IF(M3>=0.035,85,IF(M3>=0.025,70,IF(M3>=0.015,50,IF(M3>=0.005,30,IF(M3>0,10,5)))))) | O3: ='基金持仓'!D3 | P3: 0.35 | Q3: 0.25 | R3: 0.25 | S3: 0.15 | T3: =P3*G3+Q3*J3+R3*L3+S3*N3 | U3: =C3*T3
A4: ='基金持仓'!A4 | B4: ='基金持仓'!B4 | C4: ='基金持仓'!F4 | D4: ='基金持仓'!D4 | E4: 22 | F4: 0.55 | G4: =IF(F4<=0.15,100,IF(F4<=0.3,85,IF(F4<=0.5,65,IF(F4<=0.7,45,IF(F4<=0.85,25,10))))) | H4: 5.2 | I4: 0.48 | J4: =IF(I4<=0.15,100,IF(I4<=0.3,85,IF(I4<=0.5,65,IF(I4<=0.7,45,IF(I4<=0.85,25,10))))) | K4: 0.63 | L4: =IF(K4<0.5,100,IF(K4<0.8,90,IF(K4<1,80,IF(K4<1.5,60,IF(K4<2.5,35,15))))) | M4: 0.008 | N4: =IF(M4>=0.05,100,IF(M4>=0.035,85,IF(M4>=0.025,70,IF(M4>=0.015,50,IF(M4>=0.005,30,IF(M4>0,10,5)))))) | O4: ='基金持仓'!D4 | P4: 0.35 | Q4: 0.25 | R4: 0.25 | S4: 0.15 | T4: =P4*G4+Q4*J4+R4*L4+S4*N4 | U4: =C4*T4
A5: ='基金持仓'!A5 | B5: ='基金持仓'!B5 | C5: ='基金持仓'!F5 | D5: ='基金持仓'!D5 | E5: 6.5 | F5: 0.45 | G5: =IF(F5<=0.15,100,IF(F5<=0.3,85,IF(F5<=0.5,65,IF(F5<=0.7,45,IF(F5<=0.85,25,10))))) | H5: 0.85 | I5: 0.35 | J5: =IF(I5<=0.15,100,IF(I5<=0.3,85,IF(I5<=0.5,65,IF(I5<=0.7,45,IF(I5<=0.85,25,10))))) | K5: 1.08 | L5: =IF(K5<0.5,100,IF(K5<0.8,90,IF(K5<1,80,IF(K5<1.5,60,IF(K5<2.5,35,15))))) | M5: 0.048 | N5: =IF(M5>=0.05,100,IF(M5>=0.035,85,IF(M5>=0.025,70,IF(M5>=0.015,50,IF(M5>=0.005,30,IF(M5>0,10,5)))))) | O5: ='基金持仓'!D5 | P5: 0.2 | Q5: 0.4 | R5: 0.15 | S5: 0.25 | T5: =P5*G5+Q5*J5+R5*L5+S5*N5 | U5: =C5*T5
A6: ='基金持仓'!A6 | B6: ='基金持仓'!B6 | C6: ='基金持仓'!F6 | D6: ='基金持仓'!D6 | E6: 35 | F6: 0.7 | G6: =IF(F6<=0.15,100,IF(F6<=0.3,85,IF(F6<=0.5,65,IF(F6<=0.7,45,IF(F6<=0.85,25,10))))) | H6: 8.8 | I6: 0.65 | J6: =IF(I6<=0.15,100,IF(I6<=0.3,85,IF(I6<=0.5,65,IF(I6<=0.7,45,IF(I6<=0.85,25,10))))) | K6: 1.6 | L6: =IF(K6<0.5,100,IF(K6<0.8,90,IF(K6<1,80,IF(K6<1.5,60,IF(K6<2.5,35,15))))) | M6: 0.012 | N6: =IF(M6>=0.05,100,IF(M6>=0.035,85,IF(M6>=0.025,70,IF(M6>=0.015,50,IF(M6>=0.005,30,IF(M6>0,10,5)))))) | O6: ='基金持仓'!D6 | P6: 0.35 | Q6: 0.25 | R6: 0.25 | S6: 0.15 | T6: =P6*G6+Q6*J6+R6*L6+S6*N6 | U6: =C6*T6
A7: ='基金持仓'!A7 | B7: ='基金持仓'!B7 | C7: ='基金持仓'!F7 | D7: ='基金持仓'!D7 | E7: 28 | F7: 0.6 | G7: =IF(F7<=0.15,100,IF(F7<=0.3,85,IF(F7<=0.5,65,IF(F7<=0.7,45,IF(F7<=0.85,25,10))))) | H7: 3.5 | I7: 0.52 | J7: =IF(I7<=0.15,100,IF(I7<=0.3,85,IF(I7<=0.5,65,IF(I7<=0.7,45,IF(I7<=0.85,25,10))))) | K7: 1.12 | L7: =IF(K7<0.5,100,IF(K7<0.8,90,IF(K7<1,80,IF(K7<1.5,60,IF(K7<2.5,35,15))))) | M7: 0.006 | N7: =IF(M7>=0.05,100,IF(M7>=0.035,85,IF(M7>=0.025,70,IF(M7>=0.015,50,IF(M7>=0.005,30,IF(M7>0,10,5)))))) | O7: ='基金持仓'!D7 | P7: 0.35 | Q7: 0.25 | R7: 0.25 | S7: 0.15 | T7: =P7*G7+Q7*J7+R7*L7+S7*N7 | U7: =C7*T7
A8: ='基金持仓'!A8 | B8: ='基金持仓'!B8 | C8: ='基金持仓'!F8 | D8: ='基金持仓'!D8 | E8: 25 | F8: 0.65 | G8: =IF(F8<=0.15,100,IF(F8<=0.3,85,IF(F8<=0.5,65,IF(F8<=0.7,45,IF(F8<=0.85,25,10))))) | H8: 6.2 | I8: 0.55 | J8: =IF(I8<=0.15,100,IF(I8<=0.3,85,IF(I8<=0.5,65,IF(I8<=0.7,45,IF(I8<=0.85,25,10))))) | K8: 1.79 | L8: =IF(K8<0.5,100,IF(K8<0.8,90,IF(K8<1,80,IF(K8<1.5,60,IF(K8<2.5,35,15))))) | M8: 0.022 | N8: =IF(M8>=0.05,100,IF(M8>=0.035,85,IF(M8>=0.025,70,IF(M8>=0.015,50,IF(M8>=0.005,30,IF(M8>0,10,5)))))) | O8: ='基金持仓'!D8 | P8: 0.35 | Q8: 0.25 | R8: 0.25 | S8: 0.15 | T8: =P8*G8+Q8*J8+R8*L8+S8*N8 | U8: =C8*T8
A9: ='基金持仓'!A9 | B9: ='基金持仓'!B9 | C9: ='基金持仓'!F9 | D9: ='基金持仓'!D9 | E9: 55 | F9: 0.82 | G9: =IF(F9<=0.15,100,IF(F9<=0.3,85,IF(F9<=0.5,65,IF(F9<=0.7,45,IF(F9<=0.85,25,10))))) | H9: 7.5 | I9: 0.68 | J9: =IF(I9<=0.15,100,IF(I9<=0.3,85,IF(I9<=0.5,65,IF(I9<=0.7,45,IF(I9<=0.85,25,10))))) | K9: 5.5 | L9: =IF(K9<0.5,100,IF(K9<0.8,90,IF(K9<1,80,IF(K9<1.5,60,IF(K9<2.5,35,15))))) | M9: 0.005 | N9: =IF(M9>=0.05,100,IF(M9>=0.035,85,IF(M9>=0.025,70,IF(M9>=0.015,50,IF(M9>=0.005,30,IF(M9>0,10,5)))))) | O9: ='基金持仓'!D9 | P9: 0.35 | Q9: 0.25 | R9: 0.25 | S9: 0.15 | T9: =P9*G9+Q9*J9+R9*L9+S9*N9 | U9: =C9*T9
A10: ='基金持仓'!A10 | B10: ='基金持仓'!B10 | C10: ='基金持仓'!F10 | D10: ='基金持仓'!D10 | E10: 85 | F10: 0.88 | G10: =IF(F10<=0.15,100,IF(F10<=0.3,85,IF(F10<=0.5,65,IF(F10<=0.7,45,IF(F10<=0.85,25,10))))) | H10: 15 | I10: 0.85 | J10: =IF(I10<=0.15,100,IF(I10<=0.3,85,IF(I10<=0.5,65,IF(I10<=0.7,45,IF(I10<=0.85,25,10))))) | K10: 2.13 | L10: =IF(K10<0.5,100,IF(K10<0.8,90,IF(K10<1,80,IF(K10<1.5,60,IF(K10<2.5,35,15))))) | M10: 0.003 | N10: =IF(M10>=0.05,100,IF(M10>=0.035,85,IF(M10>=0.025,70,IF(M10>=0.015,50,IF(M10>=0.005,30,IF(M10>0,10,5)))))) | O10: ='基金持仓'!D10 | P10: 0.35 | Q10: 0.25 | R10: 0.25 | S10: 0.15 | T10: =P10*G10+Q10*J10+R10*L10+S10*N10 | U10: =C10*T10
A11: ='基金持仓'!A11 | B11: ='基金持仓'!B11 | C11: ='基金持仓'!F11 | D11: ='基金持仓'!D11 | E11: 18 | F11: 0.42 | G11: =IF(F11<=0.15,100,IF(F11<=0.3,85,IF(F11<=0.5,65,IF(F11<=0.7,45,IF(F11<=0.85,25,10))))) | H11: 3.8 | I11: 0.38 | J11: =IF(I11<=0.15,100,IF(I11<=0.3,85,IF(I11<=0.5,65,IF(I11<=0.7,45,IF(I11<=0.85,25,10))))) | K11: 0.33 | L11: =IF(K11<0.5,100,IF(K11<0.8,90,IF(K11<1,80,IF(K11<1.5,60,IF(K11<2.5,35,15))))) | M11: 0.006 | N11: =IF(M11>=0.05,100,IF(M11>=0.035,85,IF(M11>=0.025,70,IF(M11>=0.015,50,IF(M11>=0.005,30,IF(M11>0,10,5)))))) | O11: ='基金持仓'!D11 | P11: 0.35 | Q11: 0.25 | R11: 0.25 | S11: 0.15 | T11: =P11*G11+Q11*J11+R11*L11+S11*N11 | U11: =C11*T11
A12: ='基金持仓'!A12 | B12: ='基金持仓'!B12 | C12: ='基金持仓'!F12 | D12: ='基金持仓'!D12 | E12: 22 | F12: 0.5 | G12: =IF(F12<=0.15,100,IF(F12<=0.3,85,IF(F12<=0.5,65,IF(F12<=0.7,45,IF(F12<=0.85,25,10))))) | H12: 4.2 | I12: 0.45 | J12: =IF(I12<=0.15,100,IF(I12<=0.3,85,IF(I12<=0.5,65,IF(I12<=0.7,45,IF(I12<=0.85,25,10))))) | K12: 2.75 | L12: =IF(K12<0.5,100,IF(K12<0.8,90,IF(K12<1,80,IF(K12<1.5,60,IF(K12<2.5,35,15))))) | M12: 0.025 | N12: =IF(M12>=0.05,100,IF(M12>=0.035,85,IF(M12>=0.025,70,IF(M12>=0.015,50,IF(M12>=0.005,30,IF(M12>0,10,5)))))) | O12: ='基金持仓'!D12 | P12: 0.35 | Q12: 0.25 | R12: 0.25 | S12: 0.15 | T12: =P12*G12+Q12*J12+R12*L12+S12*N12 | U12: =C12*T12
B13: M2 综合得分 | U13: =SUM(U3:U12)

Sheet M3_舆情评分
A1: 模型3：新闻舆情与动量（默认权重20%）
A2: 代码 | B2: 名称 | C2: 权重 | D2: 正面新闻 | E2: 负面新闻 | F2: 中性新闻 | G2: 新闻情感分 | H2: 自媒体占比 | I2: 来源降级扣分 | J2: 分析师上调 | K2: 分析师下调 | L2: 总报告 | M2: 评级得分 | N2: 调研分位数 | O2: 调研得分 | P2: 资金净流入% | Q2: 资金得分 | R2: 舆情总分 | S2: 加权贡献
A3: ='基金持仓'!A3 | B3: ='基金持仓'!B3 | C3: ='基金持仓'!F3 | D3: 45 | E3: 8 | F3: 20 | G3: =(D3-E3)/(D3+E3+F3) | H3: 0.25 | I3: =IF(H3>0.6,-15,0) | J3: 3 | K3: 1 | L3: 12 | M3: =MIN(100,MAX(0,50+25*(J3-K3)/L3)) | N3: 0.75 | O3: =IF(N3>=0.9,100,IF(N3>=0.75,85,IF(N3>=0.5,65,IF(N3>=0.25,45,IF(N3>0,25,10))))) | P3: 0.008 | Q3: =IF(P3>=0.02,100,IF(P3>=0.01,85,IF(P3>=0.003,65,IF(P3>=-0.003,50,IF(P3>=-0.01,35,15))))) | R3: =0.35*(MIN(100,MAX(0,50+100*G3))+I3)+0.25*M3+0.2*O3+0.2*Q3 | S3: =C3*R3
A4: ='基金持仓'!A4 | B4: ='基金持仓'!B4 | C4: ='基金持仓'!F4 | D4: 30 | E4: 15 | F4: 18 | G4: =(D4-E4)/(D4+E4+F4) | H4: 0.35 | I4: =IF(H4>0.6,-15,0) | J4: 5 | K4: 2 | L4: 15 | M4: =MIN(100,MAX(0,50+25*(J4-K4)/L4)) | N4: 0.85 | O4: =IF(N4>=0.9,100,IF(N4>=0.75,85,IF(N4>=0.5,65,IF(N4>=0.25,45,IF(N4>0,25,10))))) | P4: -0.005 | Q4: =IF(P4>=0.02,100,IF(P4>=0.01,85,IF(P4>=0.003,65,IF(P4>=-0.003,50,IF(P4>=-0.01,35,15))))) | R4: =0.35*(MIN(100,MAX(0,50+100*G4))+I4)+0.25*M4+0.2*O4+0.2*Q4 | S4: =C4*R4
A5: ='基金持仓'!A5 | B5: ='基金持仓'!B5 | C5: ='基金持仓'!F5 | D5: 35 | E5: 10 | F5: 22 | G5: =(D5-E5)/(D5+E5+F5) | H5: 0.2 | I5: =IF(H5>0.6,-15,0) | J5: 2 | K5: 0 | L5: 8 | M5: =MIN(100,MAX(0,50+25*(J5-K5)/L5)) | N5: 0.55 | O5: =IF(N5>=0.9,100,IF(N5>=0.75,85,IF(N5>=0.5,65,IF(N5>=0.25,45,IF(N5>0,25,10))))) | P5: 0.015 | Q5: =IF(P5>=0.02,100,IF(P5>=0.01,85,IF(P5>=0.003,65,IF(P5>=-0.003,50,IF(P5>=-0.01,35,15))))) | R5: =0.35*(MIN(100,MAX(0,50+100*G5))+I5)+0.25*M5+0.2*O5+0.2*Q5 | S5: =C5*R5
A6: ='基金持仓'!A6 | B6: ='基金持仓'!B6 | C6: ='基金持仓'!F6 | D6: 28 | E6: 12 | F6: 25 | G6: =(D6-E6)/(D6+E6+F6) | H6: 0.18 | I6: =IF(H6>0.6,-15,0) | J6: 4 | K6: 1 | L6: 10 | M6: =MIN(100,MAX(0,50+25*(J6-K6)/L6)) | N6: 0.7 | O6: =IF(N6>=0.9,100,IF(N6>=0.75,85,IF(N6>=0.5,65,IF(N6>=0.25,45,IF(N6>0,25,10))))) | P6: 0.006 | Q6: =IF(P6>=0.02,100,IF(P6>=0.01,85,IF(P6>=0.003,65,IF(P6>=-0.003,50,IF(P6>=-0.01,35,15))))) | R6: =0.35*(MIN(100,MAX(0,50+100*G6))+I6)+0.25*M6+0.2*O6+0.2*Q6 | S6: =C6*R6
A7: ='基金持仓'!A7 | B7: ='基金持仓'!B7 | C7: ='基金持仓'!F7 | D7: 22 | E7: 18 | F7: 28 | G7: =(D7-E7)/(D7+E7+F7) | H7: 0.22 | I7: =IF(H7>0.6,-15,0) | J7: 3 | K7: 3 | L7: 14 | M7: =MIN(100,MAX(0,50+25*(J7-K7)/L7)) | N7: 0.5 | O7: =IF(N7>=0.9,100,IF(N7>=0.75,85,IF(N7>=0.5,65,IF(N7>=0.25,45,IF(N7>0,25,10))))) | P7: -0.008 | Q7: =IF(P7>=0.02,100,IF(P7>=0.01,85,IF(P7>=0.003,65,IF(P7>=-0.003,50,IF(P7>=-0.01,35,15))))) | R7: =0.35*(MIN(100,MAX(0,50+100*G7))+I7)+0.25*M7+0.2*O7+0.2*Q7 | S7: =C7*R7
A8: ='基金持仓'!A8 | B8: ='基金持仓'!B8 | C8: ='基金持仓'!F8 | D8: 40 | E8: 10 | F8: 18 | G8: =(D8-E8)/(D8+E8+F8) | H8: 0.28 | I8: =IF(H8>0.6,-15,0) | J8: 2 | K8: 1 | L8: 9 | M8: =MIN(100,MAX(0,50+25*(J8-K8)/L8)) | N8: 0.6 | O8: =IF(N8>=0.9,100,IF(N8>=0.75,85,IF(N8>=0.5,65,IF(N8>=0.25,45,IF(N8>0,25,10))))) | P8: 0.012 | Q8: =IF(P8>=0.02,100,IF(P8>=0.01,85,IF(P8>=0.003,65,IF(P8>=-0.003,50,IF(P8>=-0.01,35,15))))) | R8: =0.35*(MIN(100,MAX(0,50+100*G8))+I8)+0.25*M8+0.2*O8+0.2*Q8 | S8: =C8*R8
A9: ='基金持仓'!A9 | B9: ='基金持仓'!B9 | C9: ='基金持仓'!F9 | D9: 35 | E9: 8 | F9: 15 | G9: =(D9-E9)/(D9+E9+F9) | H9: 0.15 | I9: =IF(H9>0.6,-15,0) | J9: 6 | K9: 0 | L9: 12 | M9: =MIN(100,MAX(0,50+25*(J9-K9)/L9)) | N9: 0.9 | O9: =IF(N9>=0.9,100,IF(N9>=0.75,85,IF(N9>=0.5,65,IF(N9>=0.25,45,IF(N9>0,25,10))))) | P9: 0.025 | Q9: =IF(P9>=0.02,100,IF(P9>=0.01,85,IF(P9>=0.003,65,IF(P9>=-0.003,50,IF(P9>=-0.01,35,15))))) | R9: =0.35*(MIN(100,MAX(0,50+100*G9))+I9)+0.25*M9+0.2*O9+0.2*Q9 | S9: =C9*R9
A10: ='基金持仓'!A10 | B10: ='基金持仓'!B10 | C10: ='基金持仓'!F10 | D10: 25 | E10: 5 | F10: 10 | G10: =(D10-E10)/(D10+E10+F10) | H10: 0.1 | I10: =IF(H10>0.6,-15,0) | J10: 8 | K10: 0 | L10: 11 | M10: =MIN(100,MAX(0,50+25*(J10-K10)/L10)) | N10: 0.95 | O10: =IF(N10>=0.9,100,IF(N10>=0.75,85,IF(N10>=0.5,65,IF(N10>=0.25,45,IF(N10>0,25,10))))) | P10: 0.018 | Q10: =IF(P10>=0.02,100,IF(P10>=0.01,85,IF(P10>=0.003,65,IF(P10>=-0.003,50,IF(P10>=-0.01,35,15))))) | R10: =0.35*(MIN(100,MAX(0,50+100*G10))+I10)+0.25*M10+0.2*O10+0.2*Q10 | S10: =C10*R10
A11: ='基金持仓'!A11 | B11: ='基金持仓'!B11 | C11: ='基金持仓'!F11 | D11: 20 | E11: 22 | F11: 20 | G11: =(D11-E11)/(D11+E11+F11) | H11: 0.4 | I11: =IF(H11>0.6,-15,0) | J11: 4 | K11: 2 | L11: 10 | M11: =MIN(100,MAX(0,50+25*(J11-K11)/L11)) | N11: 0.65 | O11: =IF(N11>=0.9,100,IF(N11>=0.75,85,IF(N11>=0.5,65,IF(N11>=0.25,45,IF(N11>0,25,10))))) | P11: -0.015 | Q11: =IF(P11>=0.02,100,IF(P11>=0.01,85,IF(P11>=0.003,65,IF(P11>=-0.003,50,IF(P11>=-0.01,35,15))))) | R11: =0.35*(MIN(100,MAX(0,50+100*G11))+I11)+0.25*M11+0.2*O11+0.2*Q11 | S11: =C11*R11
A12: ='基金持仓'!A12 | B12: ='基金持仓'!B12 | C12: ='基金持仓'!F12 | D12: 30 | E12: 15 | F12: 25 | G12: =(D12-E12)/(D12+E12+F12) | H12: 0.25 | I12: =IF(H12>0.6,-15,0) | J12: 3 | K12: 1 | L12: 9 | M12: =MIN(100,MAX(0,50+25*(J12-K12)/L12)) | N12: 0.55 | O12: =IF(N12>=0.9,100,IF(N12>=0.75,85,IF(N12>=0.5,65,IF(N12>=0.25,45,IF(N12>0,25,10))))) | P12: 0.005 | Q12: =IF(P12>=0.02,100,IF(P12>=0.01,85,IF(P12>=0.003,65,IF(P12>=-0.003,50,IF(P12>=-0.01,35,15))))) | R12: =0.35*(MIN(100,MAX(0,50+100*G12))+I12)+0.25*M12+0.2*O12+0.2*Q12 | S12: =C12*R12
B13: M3 综合得分 | S13: =SUM(S3:S12)

Sheet M4_行业景气
A1: 模型4：行业前景与宏观匹配度（默认权重15%）
A2: 行业 | B2: 基金权重 | C2: 行业PMI | D2: PMI得分 | E2: 营收增速 | F2: 营收增速得分 | G2: ROE趋势 | H2: 趋势调整 | I2: 定量景气分 | J2: 产业周期位置 | K2: 周期得分 | L2: 景气总分 | M2: 政策支持得分 | N2: 宏观匹配调整 | O2: 行业总分 | P2: 加权贡献
A3: 食品饮料 | B3: =SUMIF('基金持仓'!D3:D12,A3,'基金持仓'!F3:F12) | C3: 0.5 | D3: =IF(C3>0.55,100,IF(C3>0.5,75,IF(C3>0.45,50,25))) | E3: 0.12 | F3: =IF(E3>=0.3,100,IF(E3>=0.2,85,IF(E3>=0.1,65,IF(E3>=0.05,45,IF(E3>=0,25,10))))) | G3: 0 | H3: =G3*10 | I3: =0.6*D3+0.4*F3+H3 | J3: 成熟期 | K3: =IF(J3="成长期",90,IF(J3="导入期",65,IF(J3="成熟期",55,IF(J3="衰退期",25,50)))) | L3: =0.6*I3+0.4*K3 | M3: 75 | N3: 5 | O3: =0.45*L3+0.3*M3+0.25*(50+N3) | P3: =B3*O3
A4: 电力设备 | B4: =SUMIF('基金持仓'!D3:D12,A4,'基金持仓'!F3:F12) | C4: 0.52 | D4: =IF(C4>0.55,100,IF(C4>0.5,75,IF(C4>0.45,50,25))) | E4: 0.08 | F4: =IF(E4>=0.3,100,IF(E4>=0.2,85,IF(E4>=0.1,65,IF(E4>=0.05,45,IF(E4>=0,25,10))))) | G4: -1 | H4: =G4*10 | I4: =0.6*D4+0.4*F4+H4 | J4: 成熟期 | K4: =IF(J4="成长期",90,IF(J4="导入期",65,IF(J4="成熟期",55,IF(J4="衰退期",25,50)))) | L4: =0.6*I4+0.4*K4 | M4: 70 | N4: 10 | O4: =0.45*L4+0.3*M4+0.25*(50+N4) | P4: =B4*O4
A5: 银行 | B5: =SUMIF('基金持仓'!D3:D12,A5,'基金持仓'!F3:F12) | C5: 0.51 | D5: =IF(C5>0.55,100,IF(C5>0.5,75,IF(C5>0.45,50,25))) | E5: 0.03 | F5: =IF(E5>=0.3,100,IF(E5>=0.2,85,IF(E5>=0.1,65,IF(E5>=0.05,45,IF(E5>=0,25,10))))) | G5: 1 | H5: =G5*10 | I5: =0.6*D5+0.4*F5+H5 | J5: 成熟期 | K5: =IF(J5="成长期",90,IF(J5="导入期",65,IF(J5="成熟期",55,IF(J5="衰退期",25,50)))) | L5: =0.6*I5+0.4*K5 | M5: 60 | N5: 15 | O5: =0.45*L5+0.3*M5+0.25*(50+N5) | P5: =B5*O5
A6: 医药生物 | B6: =SUMIF('基金持仓'!D3:D12,A6,'基金持仓'!F3:F12) | C6: 0.48 | D6: =IF(C6>0.55,100,IF(C6>0.5,75,IF(C6>0.45,50,25))) | E6: 0.05 | F6: =IF(E6>=0.3,100,IF(E6>=0.2,85,IF(E6>=0.1,65,IF(E6>=0.05,45,IF(E6>=0,25,10))))) | G6: 0 | H6: =G6*10 | I6: =0.6*D6+0.4*F6+H6 | J6: 成长期 | K6: =IF(J6="成长期",90,IF(J6="导入期",65,IF(J6="成熟期",55,IF(J6="衰退期",25,50)))) | L6: =0.6*I6+0.4*K6 | M6: 80 | N6: -5 | O6: =0.45*L6+0.3*M6+0.25*(50+N6) | P6: =B6*O6
A7: 电子 | B7: =SUMIF('基金持仓'!D3:D12,A7,'基金持仓'!F3:F12) | C7: 0.53 | D7: =IF(C7>0.55,100,IF(C7>0.5,75,IF(C7>0.45,50,25))) | E7: 0.1 | F7: =IF(E7>=0.3,100,IF(E7>=0.2,85,IF(E7>=0.1,65,IF(E7>=0.05,45,IF(E7>=0,25,10))))) | G7: 1 | H7: =G7*10 | I7: =0.6*D7+0.4*F7+H7 | J7: 成长期 | K7: =IF(J7="成长期",90,IF(J7="导入期",65,IF(J7="成熟期",55,IF(J7="衰退期",25,50)))) | L7: =0.6*I7+0.4*K7 | M7: 65 | N7: 0 | O7: =0.45*L7+0.3*M7+0.25*(50+N7) | P7: =B7*O7
A8: 计算机 | B8: =SUMIF('基金持仓'!D3:D12,A8,'基金持仓'!F3:F12) | C8: 0.55 | D8: =IF(C8>0.55,100,IF(C8>0.5,75,IF(C8>0.45,50,25))) | E8: 0.15 | F8: =IF(E8>=0.3,100,IF(E8>=0.2,85,IF(E8>=0.1,65,IF(E8>=0.05,45,IF(E8>=0,25,10))))) | G8: 0 | H8: =G8*10 | I8: =0.6*D8+0.4*F8+H8 | J8: 成长期 | K8: =IF(J8="成长期",90,IF(J8="导入期",65,IF(J8="成熟期",55,IF(J8="衰退期",25,50)))) | L8: =0.6*I8+0.4*K8 | M8: 85 | N8: -10 | O8: =0.45*L8+0.3*M8+0.25*(50+N8) | P8: =B8*O8
A9: M4 综合得分 | P9: =SUM(P3:P8)

Sheet M5_经理行为
A1: 模型5：基金经理行为一致性（默认权重15%）
A2: 评估维度 | B2: 数值 | C2: 得分 | D2: 权重 | E2: 加权得分 | F2: 说明
A3: 风格标签变化次数(近4季) | B3: 1 | C3: =MAX(0,100-25*B3) | D3: 0.3 | E3: =C3*D3 | F3: 100-25×变化次数
A4: 年化换手率 | B4: 0.85 | C4: =IF(B4<1,100,IF(B4<2,80,IF(B4<4,55,IF(B4<6,30,10)))) | D4: 0.15 | E4: =C4*D4 | F4: <100%=100, 100-200%=80, 200-400%=55
A5: 正确调仓次数/总调仓 | B5: 0.62 | C5: =MIN(100,MAX(0,50+50*(2*B5-1))) | D5: 0.15 | E5: =C5*D5 | F5: 50+50×(2×正确率-1)
A6: 言行不匹配次数 | B6: 2 | C6: =MAX(0,100-20*B6) | D6: 0.25 | E6: =C6*D6 | F6: 100-20×不匹配次数
A7: IR(信息比率) | B7: 0.45 | C7: =MIN(100,MAX(0,50+50*(B7-0.2)/(0.8-0.2))) | D7: 0.15 | E7: =C7*D7 | F7: 相对同类IR映射
A8: M5 综合得分 | E8: =SUM(E3:E7)

Sheet 动态权重
A1: 动态权重调整引擎
A3: 市场环境识别
A4: 信号 | B4: 当前值 | C4: 判断结果 | D4: 说明
A5: CSI300 PE分位数 | B5: ='假设区'!B3 | C5: =IF(B5>0.7,"高估",IF(B5<0.3,"低估","中等")) | D5: PE分位数>70%=牛市信号
A6: 60日/200日均线 | B6: ='假设区'!B8 | C6: =IF(B6>1.03,"多头排列",IF(B6<0.97,"空头排列","震荡")) | D6: >1.03多头，<0.97空头
A7: 波动率分位数 | B7: ='假设区'!B7 | C7: =IF(B7>0.75,"高波动",IF(B7<0.25,"低波动","正常")) | D7: >75%=高不确定性
A8: EPU分位数 | B8: ='假设区'!B6 | C8: =IF(B8>0.8,"高不确定性","正常") | D8: >80%=高不确定性
A10: 判定市场环境 | B10: =IF(OR(B8="高不确定性",B7="高波动"),"高不确定性",IF(AND(B5="高估",B6="多头排列"),"牛市",IF(AND(B5="低估",B6="空头排列"),"熊市",IF(B6="震荡","震荡市","正常")))) | C10: 当前市场环境
A12: 权重矩阵
A13: 市场环境 | B13: M1个股质量 | C13: M2估值 | D13: M3舆情 | E13: M4行业 | F13: M5经理
A14: 正常 | B14: 0.25 | C14: 0.25 | D14: 0.2 | E14: 0.15 | F14: 0.15
A15: 牛市 | B15: 0.15 | C15: 0.35 | D15: 0.15 | E15: 0.2 | F15: 0.15
A16: 熊市 | B16: 0.3 | C16: 0.2 | D16: 0.15 | E16: 0.2 | F16: 0.15
A17: 震荡市 | B17: 0.25 | C17: 0.2 | D17: 0.2 | E17: 0.2 | F17: 0.15
A18: 高不确定性 | B18: 0.2 | C18: 0.25 | D18: 0.15 | E18: 0.3 | F18: 0.1
A20: 当前有效权重（VLOOKUP匹配）
A21: 模型 | B21: 目标权重 | C21: 前值权重 | D21: 平滑后权重
A22: M1 | B22: =VLOOKUP(B10,$A$14:$F$18,2,FALSE) | C22: ='假设区'!B14 | D22: =0.7*B22+0.3*C22
A23: M2 | B23: =VLOOKUP(B10,$A$14:$F$18,3,FALSE) | C23: ='假设区'!B15 | D23: =0.7*B23+0.3*C23
A24: M3 | B24: =VLOOKUP(B10,$A$14:$F$18,4,FALSE) | C24: ='假设区'!B16 | D24: =0.7*B24+0.3*C24
A25: M4 | B25: =VLOOKUP(B10,$A$14:$F$18,5,FALSE) | C25: ='假设区'!B17 | D25: =0.7*B25+0.3*C25
A26: M5 | B26: =VLOOKUP(B10,$A$14:$F$18,6,FALSE) | C26: ='假设区'!B18 | D26: =0.7*B26+0.3*C26

Sheet 综合输出
A1: AI多因子透视诊断 — 综合输出
A3: 基金名称 | C3: 示例基金（华夏成长混合）
A4: 分析日期 | C4: 2026-05-23
A5: 市场环境 | C5: ='动态权重'!B10
A7: 综合评分
A8: 综合评分 | B8: 评分等级 | C8: 操作建议基调
A9: ='动态权重'!D22*'M1_个股质量评分'!AB13+'动态权重'!D23*'M2_估值评分'!U13+'动态权重'!D24*'M3_舆情评分'!S13+'动态权重'!D25*'M4_行业景气'!P9+'动态权重'!D26*'M5_经理行为'!E7 | B9: =IF(A9>=80,"优秀 ⭐⭐⭐⭐⭐",IF(A9>=70,"良好 ⭐⭐⭐⭐",IF(A9>=55,"一般 ⭐⭐⭐",IF(A9>=40,"较低 ⭐⭐","差 ⭐")))) | C9: =IF(A9>=80,"适合作为核心配置",IF(A9>=70,"可持有，关注风险点",IF(A9>=55,"观望，等待更好时机",IF(A9>=40,"建议减仓或寻找替代品","强烈建议回避"))))
A12: 五维度评分明细
A13: 评估维度 | B13: 评分 | C13: 有效权重 | D13: 加权贡献 | E13: 简评
A14: M1 个股质量 | B14: 'M1_个股质量评分'!AB13 | C14: ='动态权重'!D22 | D14: =B14*C14 | E14: 重仓股以行业龙头为主，ROE中位数18%
A15: M2 估值性价比 | B15: 'M2_估值评分'!U13 | C15: ='动态权重'!D23 | D15: =B15*C15 | E15: 持仓加权PE分位数偏高，需关注估值风险
A16: M3 新闻舆情 | B16: 'M3_舆情评分'!S13 | C16: ='动态权重'!D24 | D16: =B16*C16 | E16: 近期机构调研增加，舆情偏正面
A17: M4 行业景气 | B17: 'M4_行业景气'!P9 | C17: ='动态权重'!D25 | D17: =B17*C17 | E17: 持仓行业整体景气度中等，政策面偏暖
A18: M5 经理行为 | B18: 'M5_经理行为'!E7 | C18: ='动态权重'!D26 | D18: =B18*C18 | E18: 基金经理风格稳定，调仓节奏合理
A20: 雷达图数据（供图表使用）
A21: M1 | B21: M2 | C21: M3 | D21: M4 | E21: M5 | F21: 综合
A22: =B14 | B22: =B15 | C22: =B16 | D22: =B17 | E22: =B18 | F22: =A9
A24: 最终建议
A25: 操作建议 | B25: 核心理由
A26: =IF(A9>=80,"持有/加仓",IF(A9>=70,"持有",IF(A9>=55,"观望/分批调整",IF(A9>=40,"减仓","卖出")))) | B26: =IF(A9>=80,"持仓公司质量优秀，估值合理，适合作为核心资产配置",IF(A9>=70,"持仓质量较好但部分估值偏高，可持有观察",IF(A9>=55,"持仓优劣参半，建议等待更好的入场时机",IF(A9>=40,"持仓整体质量偏低或估值过高，建议逐步减仓","持仓质量与估值均不理想，建议回避"))))
A28: 需关注的风险点
A29: 1. PE分位数若继续上行至85%以上，建议减仓
A30: 2. 关注前三大重仓股下季度财报增速是否放缓
A31: 3. 若市场环境切换为"高不确定性"，需重新评估行业配置
A32: 4. 基金经理若出现风格漂移（标签变化≥2次），需警惕
